MapCanvasGTK/MapCanvas.py
MapCanvasGTK/__init__.py
MapCanvasGTK-0.0.1.dist-info/LICENSE.txt
MapCanvasGTK-0.0.1.dist-info/METADATA
MapCanvasGTK-0.0.1.dist-info/WHEEL
MapCanvasGTK-0.0.1.dist-info/top_level.txt
MapCanvasGTK-0.0.1.dist-info/RECORD
